{
  "strategy": {
    "settings": {
      "benchmark": "000300.XSHG",
      "options": {
        "avoid_future_data": false,
        "match_by_signal": false,
        "order_match_mode": "immediate",
        "order_volume_ratio": 0.25,
        "use_real_price": true
      },
      "order_cost": {
        "fund": {
          "close_commission": 0.0003,
          "close_tax": 0.0,
          "close_today_commission": 0.0,
          "commission_type": "by_money",
          "min_commission": 5.0,
          "open_commission": 0.0003,
          "open_tax": 0.0
        },
        "money_market_fund": {
          "close_commission": 0.0,
          "close_tax": 0.0,
          "close_today_commission": 0.0,
          "commission_type": "by_money",
          "min_commission": 0.0,
          "open_commission": 0.0,
          "open_tax": 0.0
        },
        "stock": {
          "close_commission": 0.0003,
          "close_tax": 0.001,
          "close_today_commission": 0.0,
          "commission_type": "by_money",
          "min_commission": 5.0,
          "open_commission": 0.0003,
          "open_tax": 0.0
        }
      }
    },
    "strategy_hash": "def56c1eded3eff640210b9772041b71",
    "tasks": [
      {
        "enabled": true,
        "func": "trade",
        "module": "strategy",
        "monthday": null,
        "schedule_type": "daily",
        "time": "open",
        "weekday": null
      }
    ],
    "version": 1
  }
}